{
  "archivedAt": "2026-04-20T15:27:06.698Z",
  "sourceUrl": "https://www.bosthlm.se/1911307/john-lodens-vag-24-1911307",
  "meta": {
    "title": "BOSTHLM Fastighetsmäklare",
    "price": "SÅLD",
    "facts": [
      "MÄKLARE\nSARA WENNERTORP",
      "FAKTA",
      "DELA",
      "FACEBOOK",
      "X",
      "EMAIL",
      "Dela",
      "Facebook",
      "Email",
      "ANTAL RUM:\t6 rum och kök varav 3 - 4 sovrum\nVÅNINGSPLAN:\t3 våningar , hiss finns ej\nBOAREA:\t147 Kvm\nMÅNADSAVGIFT:\t7 727 kr (Renhållning ingår)\nSLUTPRIS:\t9.900.000 kr Såld",
      "ANTAL RUM:\t6 rum och kök varav 3 - 4 sovrum",
      "ANTAL RUM:",
      "6 rum och kök varav 3 - 4 sovrum",
      "VÅNINGSPLAN:\t3 våningar , hiss finns ej",
      "VÅNINGSPLAN:",
      "3 våningar , hiss finns ej",
      "BOAREA:\t147 Kvm",
      "BOAREA:",
      "147 Kvm",
      "MÅNADSAVGIFT:",
      "7 727 kr (Renhållning ingår)",
      "SLUTPRIS:",
      "9.900.000 kr Såld",
      "SÅLD",
      "ANSVARIG MÄKLARE\nSara Wennertorp\n073-346 46 49\n|\nsara@bosthlm.se",
      "Våra kontor",
      "SÖDERMALM\nSwedenborgsgatan 3\n08-410 205 01\nsodermalm@bosthlm.se",
      "HAMMARBY SJÖSTAD\nTimmermansgatan 36C\n08-410 205 01\nsodermalm@bosthlm.se",
      "KUNGSHOLMEN\nHantverkargatan 69B\n08-721 77 70\nkungsholmen@bosthlm.se",
      "NACKA\nVikdalsvägen 3\n08-83 37 33\nnacka@bosthlm.se",
      "ÅRSTA\nJohanneshovsvägen 139A\n08-66 80 700\narsta@bosthlm.se",
      "HAMMARBYHÖJDEN\nFinn Malmgrens plan 5-7\n08-730 10 20\nhammarbyhojden@bosthlm.se",
      "BROMMA\nBällstavägen 6\n08-34 73 15\nbromma@bosthlm.se",
      "ÄLVSJÖ\nKabelverksgatan 1\n08-39 44 30\nalsvjo@bosthlm.se",
      "HANINGE\nHandenterminalen 2\n08-400 205 05\nhaninge@bosthlm.se",
      "BANDHAGEN\nMosstenabacken 2\n08-39 44 30\nbandhagen@bosthlm.se",
      "HÄGERSTEN\nTellusborgsvägen 44\n08-85 84 44\nhagersten@bosthlm.se",
      "E-post",
      "kontakt@bosthlm.se",
      "Telefon",
      "08-410 205 01"
    ],
    "kvPairs": [
      {
        "label": "DELA",
        "value": "FACEBOOK"
      },
      {
        "label": "Dela",
        "value": "Facebook"
      },
      {
        "label": "Våra kontor",
        "value": "SÖDERMALM\nSwedenborgsgatan 3\n08-410 205 01\nsodermalm@bosthlm.se"
      },
      {
        "label": "E-post",
        "value": "kontakt@bosthlm.se"
      },
      {
        "label": "Telefon",
        "value": "08-410 205 01"
      },
      {
        "label": "ANTAL RUM:",
        "value": "6 rum och kök varav 3 - 4 sovrum"
      },
      {
        "label": "VÅNINGSPLAN:",
        "value": "3 våningar , hiss finns ej"
      },
      {
        "label": "BOAREA:",
        "value": "147 Kvm"
      },
      {
        "label": "MÅNADSAVGIFT:",
        "value": "7 727 kr (Renhållning ingår)"
      },
      {
        "label": "SLUTPRIS:",
        "value": "9.900.000 kr Såld"
      }
    ],
    "broker": "073-346 46 49\n|\nsara@bosthlm.se",
    "viewing": "OBJEKTET SÅLDES I APRIL 2026.\n\nVILL DU VÄRDERA DIN EGEN BOSTAD?\nFRI VÄRDERING"
  },
  "images": [
    {
      "url": "https://www.bosthlm.se/image/resize/1920/0/images03//192/400475/1911307/highres/22014459.jpg",
      "localPath": "assets/images/22014459.jpg",
      "filename": "22014459.jpg"
    },
    {
      "url": "https://www.bosthlm.se/image/resize/1920/0/images03/192/400475/1911307/highres/22014465.jpg",
      "localPath": "assets/images/22014465.jpg",
      "filename": "22014465.jpg"
    },
    {
      "url": "https://www.bosthlm.se/image/resize/1920/0/images03/192/400475/1911307/highres/22014463.jpg",
      "localPath": "assets/images/22014463.jpg",
      "filename": "22014463.jpg"
    },
    {
      "url": "https://www.bosthlm.se/image/resize/115/0/images03//192/user/4575.jpg",
      "localPath": "assets/images/4575.jpg",
      "filename": "4575.jpg"
    },
    {
      "url": "https://www.bosthlm.se/image/resize/230/0/images03//192/user/4575.jpg",
      "localPath": "assets/images/4575_1.jpg",
      "filename": "4575_1.jpg"
    },
    {
      "url": "https://www.bosthlm.se/image/resize/1920/0/images03//192/400475/1911307/highres/22014469.jpg",
      "localPath": "assets/images/22014469.jpg",
      "filename": "22014469.jpg"
    },
    {
      "url": "https://www.bosthlm.se/image/resize/1920/0/images03//192/400475/1911307/highres/22014465.jpg",
      "localPath": "assets/images/22014465_1.jpg",
      "filename": "22014465_1.jpg"
    },
    {
      "url": "https://www.bosthlm.se/image/resize/1920/0/images03//192/400475/1911307/highres/22014463.jpg",
      "localPath": "assets/images/22014463_1.jpg",
      "filename": "22014463_1.jpg"
    },
    {
      "url": "https://www.bosthlm.se/image/resize/1920/0/images03//192/400475/1911307/highres/22014481.jpg",
      "localPath": "assets/images/22014481.jpg",
      "filename": "22014481.jpg"
    },
    {
      "url": "https://www.bosthlm.se/image/resize/1920/0/images03//192/400475/1911307/highres/22014477.jpg",
      "localPath": "assets/images/22014477.jpg",
      "filename": "22014477.jpg"
    },
    {
      "url": "https://www.bosthlm.se/image/resize/1920/0/images03//192/400475/1911307/highres/22014471.jpg",
      "localPath": "assets/images/22014471.jpg",
      "filename": "22014471.jpg"
    },
    {
      "url": "https://www.bosthlm.se/image/resize/1920/0/images03//192/400475/1911307/highres/22014567.jpg",
      "localPath": "assets/images/22014567.jpg",
      "filename": "22014567.jpg"
    },
    {
      "url": "https://www.bosthlm.se/image/resize/1920/0/images03//192/400475/1911307/highres/22014475.jpg",
      "localPath": "assets/images/22014475.jpg",
      "filename": "22014475.jpg"
    },
    {
      "url": "https://www.bosthlm.se/image/resize/1920/0/images03//192/400475/1911307/highres/22014579.jpg",
      "localPath": "assets/images/22014579.jpg",
      "filename": "22014579.jpg"
    },
    {
      "url": "https://www.bosthlm.se/image/resize/1920/0/images03//192/400475/1911307/highres/22014473.jpg",
      "localPath": "assets/images/22014473.jpg",
      "filename": "22014473.jpg"
    },
    {
      "url": "https://www.bosthlm.se/image/resize/1920/0/images03//192/400475/1911307/highres/22014533.jpg",
      "localPath": "assets/images/22014533.jpg",
      "filename": "22014533.jpg"
    },
    {
      "url": "https://www.bosthlm.se/image/resize/1920/0/images03//192/400475/1911307/highres/22014455.jpg",
      "localPath": "assets/images/22014455.jpg",
      "filename": "22014455.jpg"
    },
    {
      "url": "https://www.bosthlm.se/image/resize/1920/0/images03//192/400475/1911307/highres/22014513.jpg",
      "localPath": "assets/images/22014513.jpg",
      "filename": "22014513.jpg"
    },
    {
      "url": "https://www.bosthlm.se/image/resize/1920/0/images03//192/400475/1911307/highres/22014515.jpg",
      "localPath": "assets/images/22014515.jpg",
      "filename": "22014515.jpg"
    },
    {
      "url": "https://www.bosthlm.se/image/resize/1920/0/images03//192/400475/1911307/highres/22014517.jpg",
      "localPath": "assets/images/22014517.jpg",
      "filename": "22014517.jpg"
    },
    {
      "url": "https://www.bosthlm.se/image/resize/1920/0/images03//192/400475/1911307/highres/22014583.jpg",
      "localPath": "assets/images/22014583.jpg",
      "filename": "22014583.jpg"
    },
    {
      "url": "https://www.bosthlm.se/image/resize/1920/0/images03//192/400475/1911307/highres/22014559.jpg",
      "localPath": "assets/images/22014559.jpg",
      "filename": "22014559.jpg"
    },
    {
      "url": "https://www.bosthlm.se/image/resize/1920/0/images03//192/400475/1911307/highres/22014511.jpg",
      "localPath": "assets/images/22014511.jpg",
      "filename": "22014511.jpg"
    },
    {
      "url": "https://www.bosthlm.se/image/resize/1920/0/images03//192/400475/1911307/highres/22014555.jpg",
      "localPath": "assets/images/22014555.jpg",
      "filename": "22014555.jpg"
    },
    {
      "url": "https://www.bosthlm.se/image/resize/1920/0/images03//192/400475/1911307/highres/22014487.jpg",
      "localPath": "assets/images/22014487.jpg",
      "filename": "22014487.jpg"
    },
    {
      "url": "https://www.bosthlm.se/image/resize/1920/0/images03//192/400475/1911307/highres/22014509.jpg",
      "localPath": "assets/images/22014509.jpg",
      "filename": "22014509.jpg"
    },
    {
      "url": "https://www.bosthlm.se/image/resize/1920/0/images03//192/400475/1911307/highres/22014489.jpg",
      "localPath": "assets/images/22014489.jpg",
      "filename": "22014489.jpg"
    },
    {
      "url": "https://www.bosthlm.se/image/resize/1920/0/images03//192/400475/1911307/highres/22014561.jpg",
      "localPath": "assets/images/22014561.jpg",
      "filename": "22014561.jpg"
    },
    {
      "url": "https://www.bosthlm.se/image/resize/1920/0/images03//192/400475/1911307/highres/22014497.jpg",
      "localPath": "assets/images/22014497.jpg",
      "filename": "22014497.jpg"
    },
    {
      "url": "https://www.bosthlm.se/image/resize/1920/0/images03//192/400475/1911307/highres/22014571.jpg",
      "localPath": "assets/images/22014571.jpg",
      "filename": "22014571.jpg"
    },
    {
      "url": "https://www.bosthlm.se/image/resize/1920/0/images03//192/400475/1911307/highres/22014503.jpg",
      "localPath": "assets/images/22014503.jpg",
      "filename": "22014503.jpg"
    },
    {
      "url": "https://www.bosthlm.se/image/resize/1920/0/images03//192/400475/1911307/highres/22014499.jpg",
      "localPath": "assets/images/22014499.jpg",
      "filename": "22014499.jpg"
    },
    {
      "url": "https://www.bosthlm.se/image/resize/1920/0/images03//192/400475/1911307/highres/22014493.jpg",
      "localPath": "assets/images/22014493.jpg",
      "filename": "22014493.jpg"
    },
    {
      "url": "https://www.bosthlm.se/image/resize/1920/0/images03//192/400475/1911307/highres/22014505.jpg",
      "localPath": "assets/images/22014505.jpg",
      "filename": "22014505.jpg"
    },
    {
      "url": "https://www.bosthlm.se/image/resize/1920/0/images03//192/400475/1911307/highres/22014585.jpg",
      "localPath": "assets/images/22014585.jpg",
      "filename": "22014585.jpg"
    },
    {
      "url": "https://www.bosthlm.se/image/resize/1920/0/images03//192/400475/1911307/highres/22014501.jpg",
      "localPath": "assets/images/22014501.jpg",
      "filename": "22014501.jpg"
    },
    {
      "url": "https://www.bosthlm.se/image/resize/1920/0/images03//192/400475/1911307/highres/22014589.jpg",
      "localPath": "assets/images/22014589.jpg",
      "filename": "22014589.jpg"
    },
    {
      "url": "https://www.bosthlm.se/image/resize/1920/0/images03//192/400475/1911307/highres/22014485.jpg",
      "localPath": "assets/images/22014485.jpg",
      "filename": "22014485.jpg"
    },
    {
      "url": "https://www.bosthlm.se/image/resize/1920/0/images03//192/400475/1911307/highres/22014483.jpg",
      "localPath": "assets/images/22014483.jpg",
      "filename": "22014483.jpg"
    },
    {
      "url": "https://www.bosthlm.se/image/resize/1920/0/images03//192/400475/1911307/highres/22014461.jpg",
      "localPath": "assets/images/22014461.jpg",
      "filename": "22014461.jpg"
    },
    {
      "url": "https://www.bosthlm.se/image/resize/1920/0/images03//192/400475/1911307/highres/22014575.jpg",
      "localPath": "assets/images/22014575.jpg",
      "filename": "22014575.jpg"
    },
    {
      "url": "https://www.bosthlm.se/image/resize/1920/0/images03//192/400475/1911307/highres/22014523.jpg",
      "localPath": "assets/images/22014523.jpg",
      "filename": "22014523.jpg"
    },
    {
      "url": "https://www.bosthlm.se/image/resize/1920/0/images03//192/400475/1911307/highres/22014519.jpg",
      "localPath": "assets/images/22014519.jpg",
      "filename": "22014519.jpg"
    },
    {
      "url": "https://www.bosthlm.se/image/resize/1920/0/images03//192/400475/1911307/highres/22014457.jpg",
      "localPath": "assets/images/22014457.jpg",
      "filename": "22014457.jpg"
    },
    {
      "url": "https://www.bosthlm.se/image/resize/1920/0/images03//192/400475/1911307/highres/22463331.jpg",
      "localPath": "assets/images/22463331.jpg",
      "filename": "22463331.jpg"
    },
    {
      "url": "https://www.bosthlm.se/image/resize/1920/0/images03//192/400475/1911307/highres/22463335.jpg",
      "localPath": "assets/images/22463335.jpg",
      "filename": "22463335.jpg"
    },
    {
      "url": "https://www.bosthlm.se/image/resize/1920/0/images03//192/400475/1911307/highres/21965973.jpg",
      "localPath": "assets/images/21965973.jpg",
      "filename": "21965973.jpg"
    },
    {
      "url": "https://www.bosthlm.se/image/resize/1920/0/images03//192/400475/1911307/highres/21965975.jpg",
      "localPath": "assets/images/21965975.jpg",
      "filename": "21965975.jpg"
    },
    {
      "url": "https://www.bosthlm.se/image/resize/1920/0/images03//192/400475/1911307/highres/21965979.jpg",
      "localPath": "assets/images/21965979.jpg",
      "filename": "21965979.jpg"
    },
    {
      "url": "https://www.bosthlm.se/image/resize/1920/0/images03//192/400475/1911307/highres/21965985.jpg",
      "localPath": "assets/images/21965985.jpg",
      "filename": "21965985.jpg"
    },
    {
      "url": "https://www.bosthlm.se/image/resize/1920/0/images03//192/400475/1911307/highres/22557091.jpg",
      "localPath": "assets/images/22557091.jpg",
      "filename": "22557091.jpg"
    },
    {
      "url": "https://www.bosthlm.se/image/resize/1920/0/images03//192/400475/1911307/highres/22557095.jpg",
      "localPath": "assets/images/22557095.jpg",
      "filename": "22557095.jpg"
    },
    {
      "url": "https://www.bosthlm.se/image/resize/1920/0/images03//192/400475/1911307/highres/22557097.jpg",
      "localPath": "assets/images/22557097.jpg",
      "filename": "22557097.jpg"
    }
  ],
  "documents": []
}